hyko_sdk_test_2/__init__.py
hyko_sdk_test_2/function.py
hyko_sdk_test_2/io.py
hyko_sdk_test_2/metadata.py
hyko_sdk_test_2/py.typed
hyko_sdk_test_2/types.py
hyko_sdk_test_2/utils.py
hyko_sdk_test_2-0.4.21.dist-info/METADATA
hyko_sdk_test_2-0.4.21.dist-info/WHEEL
hyko_sdk_test_2-0.4.21.dist-info/RECORD
