Metadata-Version: 2.1
Name: hyko-sdk-test-2
Version: 0.4.21
Summary: Hyko's Software Development Kit
Author: Ouassim Abdelmalek Ghribi
Author-email: oag@big-mama.io
Requires-Python: >=3.9,<4.0
Classifier: Programming Language :: Python :: 3
Classifier: Programming Language :: Python :: 3.9
Classifier: Programming Language :: Python :: 3.10
Classifier: Programming Language :: Python :: 3.11
Requires-Dist: fastapi (>=0.100.1,<0.101.0)
Requires-Dist: h2 (>=4.1.0,<5.0.0)
Requires-Dist: httpx (>=0.24.1,<0.25.0)
Requires-Dist: numpy (==1.25.2)
Requires-Dist: pillow (>=10.0.0,<11.0.0)
Requires-Dist: pymongo (>=4.5.0,<5.0.0)
Requires-Dist: soundfile (>=0.12.1,<0.13.0)
Requires-Dist: tqdm (>=4.0,<5.0)
